{
  "question": "Welches Gebäude in Bamberg, Deutschland, beherbergt die Grabstätte des einzigen nördlich der Alpen begrabenen Papstes?",
  "true_answer": "Der Bamberger Dom",
  "asked_language_name": "Swedish",
  "asked_question_translated": "I vilken byggnad i Bamberg, Tyskland, finns graven till den enda påve som begravts norr om Alperna?",
  "answer_ranking": 10,
  "answer": "Graven till den enda påve som begravts norr om Alperna, Clemens II, finns i Bamberger Dom (Bambergs katedral) i Bamberg, Tyskland.",
  "answer_translated_eng": "The tomb of the only pope buried north of the Alps, Clement II, is in Bamberger Dom (Bamberg Cathedral) in Bamberg, Germany."
}