{
  "question": "Wie viele Fachwerkhäuser hat die Altstadt von Bamberg, Deutschland?",
  "true_answer": "Ungefähr 2.400 Fachwerkhäuser",
  "asked_language_name": "Danish",
  "asked_question_translated": "Hvor mange bindingsværkshuse er der i den gamle bykerne i Bamberg, Tyskland?",
  "answer_ranking": 9,
  "answer": "Den gamle bykerne i Bamberg, Tyskland har omkring 2.300 bindingsværkshuse.",
  "answer_translated_eng": "The old city centre of Bamberg, Germany has around 2,300 half-timbered houses."
}