{
  "question": "What significant geographical feature is Banská Bystrica, Slovakia located at?",
  "true_answer": "At the confluence of the Hron and Bystrica rivers.",
  "asked_language_name": "Chinese",
  "asked_question_translated": "斯洛伐克班斯卡-比斯特里察（Banská Bystrica）位于什么重要的地理位置？",
  "answer_ranking": 1,
  "answer": "斯洛伐克班斯卡-比斯特里察位于斯洛伐克中部的赫龙河畔，四周环绕着低塔特拉山和克伦山脉，是国家的中心地点之一。",
  "answer_translated_eng": "Located in central Slovakia on the banks of the Heron River and surrounded by the Low Tatras and the Keren Mountains, Banská Bystrica Slovakia is one of the country's central locations."
}