{
  "question": "Name the important tourist attractions in Teruel, Spain.",
  "true_answer": "Mausoleum of the Lovers of Teruel, El Torico, and Dinópolis.",
  "asked_language_name": "Hungarian",
  "asked_question_translated": "Nevezze meg a spanyolországi Teruel fontos turisztikai látványosságait.",
  "answer_ranking": 7,
  "answer": "A spanyolországi Teruel fontos turisztikai látványosságai közé tartoznak a Mudejár építészet remekei, mint a Teruel székesegyház és a Torre de El Salvador, valamint a Dinópolis dinoszaurusz park.",
  "answer_translated_eng": "Important tourist attractions in Teruel, Spain include Mudejar architecture such as the Teruel Cathedral and the Torre de El Salvador, as well as the Dinópolis dinosaur park."
}