{
  "question": "How many hours of daylight does Uppsala, Sweden receive during the summer solstice?",
  "true_answer": "Approximately 18 hours",
  "asked_language_name": "Bulgarian",
  "asked_question_translated": "Колко часа дневна светлина има в Упсала, Швеция, по време на лятното слънцестоене?",
  "answer_ranking": 9,
  "answer": "По време на лятното слънцестоене в Упсала, Швеция, има около 18 часа и 45 минути дневна светлина.",
  "answer_translated_eng": "During the summer solstice in Uppsala, Sweden, there are about 18 hours and 45 minutes of daylight."
}