{
  "question": "Name two notable lakes surrounding Trakai, Lithuania.",
  "true_answer": "Galvė Lake and Lukos Lake (also known as Bernardinų Lake).",
  "asked_language_name": "Turkish",
  "asked_question_translated": "Litvanya'nın Trakai kentini çevreleyen iki önemli gölün adı.",
  "answer_ranking": 10,
  "answer": "Litvanya'nın Trakai kentini çevreleyen iki önemli göl Galvė Gölü ve Bernardinai Gölü'dür.",
  "answer_translated_eng": "Two important lakes surrounding the Lithuanian city of Trakai are Lake Galvė and Lake Bernardinai."
}