{
  "question": "Wie viele Fachwerkhäuser hat die Altstadt von Bamberg, Deutschland?",
  "true_answer": "Ungefähr 2.400 Fachwerkhäuser",
  "asked_language_name": "Latvian",
  "asked_question_translated": "Cik daudz mūra māju ir Bambergas vecpilsētas centrā Vācijā?",
  "answer_ranking": 3,
  "answer": "Bambergas vecpilsētas centrā Vācijā ir vairāk nekā 2 400 vēsturisko ēku, no kurām daudzas ir mūra mājas.",
  "answer_translated_eng": "Bamberg's old town centre has more than 2,400 historic buildings, many of which are stone houses."
}